scannertools/__init__.py
scannertools/audio.py
scannertools/bboxes.py
scannertools/clothing_detection.py
scannertools/face_detection.py
scannertools/face_embedding.py
scannertools/gender_detection.py
scannertools/kube.py
scannertools/object_detection.py
scannertools/optical_flow.py
scannertools/pose_detection.py
scannertools/prelude.py
scannertools/shot_detection.py
scannertools/tf_vis_utils.py
scannertools/video.py
scannertools/vis.py
scannertools-0.2.15.dist-info/DESCRIPTION.rst
scannertools-0.2.15.dist-info/METADATA
scannertools-0.2.15.dist-info/RECORD
scannertools-0.2.15.dist-info/WHEEL
scannertools-0.2.15.dist-info/metadata.json
scannertools-0.2.15.dist-info/top_level.txt
